itables/__init__.py
itables/config.py
itables/dash.py
itables/datatables_format.py
itables/downsample.py
itables/interactive.py
itables/javascript.py
itables/options.py
itables/py.typed
itables/sample_dfs.py
itables/sample_pandas_dfs.py
itables/sample_polars_dfs.py
itables/shiny.py
itables/show_config.py
itables/streamlit.py
itables/typing.py
itables/utils.py
itables/version.py
itables/html/datatables_template.html
itables/html/datatables_template_offline.html
itables/html/dt_bundle.css
itables/html/dt_bundle.js
itables/html/init_datatables.html
itables/html/init_notebook_offline.html
itables/itables_for_streamlit/asset-manifest.json
itables/itables_for_streamlit/index.html
itables/itables_for_streamlit/static/css/main.d9f03cb9.css
itables/itables_for_streamlit/static/css/main.d9f03cb9.css.map
itables/itables_for_streamlit/static/js/main.978ec6e6.js
itables/itables_for_streamlit/static/js/main.978ec6e6.js.LICENSE.txt
itables/itables_for_streamlit/static/js/main.978ec6e6.js.map
itables/logo/loading.svg
itables/logo/logo.svg
itables/logo/text.svg
itables/logo/wide.svg
itables/logo/with_text.svg
itables/samples/countries.csv
itables/samples/indicators.csv
itables/samples/population.csv
itables/widget/__init__.py
itables/widget/static/widget.css
itables/widget/static/widget.js
itables_for_dash/ITable.py
itables_for_dash/__init__.py
itables_for_dash/_imports_.py
itables_for_dash/async-ITable.js
itables_for_dash/async-ITable.js.LICENSE.txt
itables_for_dash/async-ITable.js.map
itables_for_dash/itables_for_dash.min.js
itables_for_dash/itables_for_dash.min.js.map
itables_for_dash/metadata.json
itables_for_dash/package-info.json
itables_for_dash/properties.py
itables_for_dash/py.typed
itables-2.6.2.dist-info/METADATA
itables-2.6.2.dist-info/WHEEL
itables-2.6.2.dist-info/licenses/LICENSE
itables-2.6.2.dist-info/RECORD
