Metadata-Version: 2.4
Name: itables
Version: 2.6.2
Summary: Python DataFrames as interactive DataTables
Project-URL: Homepage, https://mwouts.github.io/itables/
Project-URL: Documentation, https://mwouts.github.io/itables
Project-URL: Repository, https://github.com/mwouts/itables.git
Project-URL: Issues, https://github.com/mwouts/itables/issues
Project-URL: Changelog, https://github.com/mwouts/itables/blob/main/docs/changelog.md
Author-email: Marc Wouts <marc.wouts@gmail.com>
Maintainer-email: Marc Wouts <marc.wouts@gmail.com>
License: MIT License
License-File: LICENSE
Keywords: DataTables,Interactive,Javascript,Narwhals,Pandas,Polars
Classifier: Development Status :: 5 - Production/Stable
Classifier: Framework :: Dash
Classifier: Framework :: Jupyter
Classifier: Intended Audience :: Developers
Classifier: Intended Audience :: Science/Research
Classifier: License :: OSI Approved :: MIT License
Classifier: Programming Language :: Python
Classifier: Programming Language :: Python :: 3
Classifier: Programming Language :: Python :: 3.9
Classifier: Programming Language :: Python :: 3.10
Classifier: Programming Language :: Python :: 3.11
Classifier: Programming Language :: Python :: 3.12
Classifier: Programming Language :: Python :: 3.13
Classifier: Programming Language :: Python :: 3.14
Classifier: Typing :: Typed
Requires-Python: >=3.9
Provides-Extra: all
Requires-Dist: anywidget; extra == 'all'
Requires-Dist: dash; extra == 'all'
Requires-Dist: ipython; extra == 'all'
Requires-Dist: marimo; extra == 'all'
Requires-Dist: matplotlib; extra == 'all'
Requires-Dist: modin[dask]; extra == 'all'
Requires-Dist: narwhals; extra == 'all'
Requires-Dist: pandas; extra == 'all'
Requires-Dist: platformdirs; extra == 'all'
Requires-Dist: polars; extra == 'all'
Requires-Dist: pyarrow; extra == 'all'
Requires-Dist: pytz; extra == 'all'
Requires-Dist: shiny; extra == 'all'
Requires-Dist: shinywidgets; extra == 'all'
Requires-Dist: streamlit; extra == 'all'
Requires-Dist: tomli; (python_version < '3.11') and extra == 'all'
Requires-Dist: traitlets; extra == 'all'
Requires-Dist: typeguard>=4.4.1; extra == 'all'
Requires-Dist: typing-extensions; extra == 'all'
Requires-Dist: typing-extensions; (python_version < '3.11') and extra == 'all'
Requires-Dist: world-bank-data; extra == 'all'
Provides-Extra: check-type
Requires-Dist: typeguard>=4.4.1; extra == 'check-type'
Provides-Extra: config
Requires-Dist: platformdirs; extra == 'config'
Requires-Dist: tomli; (python_version < '3.11') and extra == 'config'
Provides-Extra: dash
Requires-Dist: dash; extra == 'dash'
Requires-Dist: typing-extensions; extra == 'dash'
Provides-Extra: dev
Requires-Dist: anywidget; extra == 'dev'
Requires-Dist: dash; extra == 'dev'
Requires-Dist: ipykernel; extra == 'dev'
Requires-Dist: ipython; extra == 'dev'
Requires-Dist: jupyterlab; extra == 'dev'
Requires-Dist: jupytext; extra == 'dev'
Requires-Dist: marimo; extra == 'dev'
Requires-Dist: matplotlib; extra == 'dev'
Requires-Dist: modin[dask]; extra == 'dev'
Requires-Dist: narwhals; extra == 'dev'
Requires-Dist: nbconvert; extra == 'dev'
Requires-Dist: pandas; extra == 'dev'
Requires-Dist: pandas-stubs; extra == 'dev'
Requires-Dist: platformdirs; extra == 'dev'
Requires-Dist: polars; extra == 'dev'
Requires-Dist: pyarrow; extra == 'dev'
Requires-Dist: pyright; extra == 'dev'
Requires-Dist: pytest; extra == 'dev'
Requires-Dist: pytest-cov; extra == 'dev'
Requires-Dist: pytest-xdist; extra == 'dev'
Requires-Dist: pytz; extra == 'dev'
Requires-Dist: requests; extra == 'dev'
Requires-Dist: shiny; extra == 'dev'
Requires-Dist: shinywidgets; extra == 'dev'
Requires-Dist: streamlit; extra == 'dev'
Requires-Dist: tomli; (python_version < '3.11') and extra == 'dev'
Requires-Dist: traitlets; extra == 'dev'
Requires-Dist: typeguard>=4.4.1; extra == 'dev'
Requires-Dist: typing-extensions; extra == 'dev'
Requires-Dist: typing-extensions; (python_version < '3.11') and extra == 'dev'
Requires-Dist: watchfiles; extra == 'dev'
Requires-Dist: world-bank-data; extra == 'dev'
Provides-Extra: marimo
Requires-Dist: marimo; extra == 'marimo'
Provides-Extra: narwhals
Requires-Dist: narwhals; extra == 'narwhals'
Provides-Extra: notebook
Requires-Dist: ipython; extra == 'notebook'
Provides-Extra: other-dataframes
Requires-Dist: modin[dask]; extra == 'other-dataframes'
Requires-Dist: narwhals; extra == 'other-dataframes'
Requires-Dist: pyarrow; extra == 'other-dataframes'
Provides-Extra: pandas
Requires-Dist: pandas; extra == 'pandas'
Provides-Extra: polars
Requires-Dist: polars; extra == 'polars'
Provides-Extra: samples
Requires-Dist: pytz; extra == 'samples'
Requires-Dist: world-bank-data; extra == 'samples'
Provides-Extra: shiny
Requires-Dist: shiny; extra == 'shiny'
Requires-Dist: shinywidgets; extra == 'shiny'
Provides-Extra: streamlit
Requires-Dist: streamlit; extra == 'streamlit'
Provides-Extra: style
Requires-Dist: matplotlib; extra == 'style'
Requires-Dist: pandas; extra == 'style'
Provides-Extra: test-all
Requires-Dist: anywidget; extra == 'test-all'
Requires-Dist: dash; extra == 'test-all'
Requires-Dist: ipykernel; extra == 'test-all'
Requires-Dist: ipython; extra == 'test-all'
Requires-Dist: jupytext; extra == 'test-all'
Requires-Dist: marimo; extra == 'test-all'
Requires-Dist: matplotlib; extra == 'test-all'
Requires-Dist: modin[dask]; extra == 'test-all'
Requires-Dist: narwhals; extra == 'test-all'
Requires-Dist: nbconvert; extra == 'test-all'
Requires-Dist: pandas; extra == 'test-all'
Requires-Dist: platformdirs; extra == 'test-all'
Requires-Dist: polars; extra == 'test-all'
Requires-Dist: pyarrow; extra == 'test-all'
Requires-Dist: pytest; extra == 'test-all'
Requires-Dist: pytest-cov; extra == 'test-all'
Requires-Dist: pytest-xdist; extra == 'test-all'
Requires-Dist: pytz; extra == 'test-all'
Requires-Dist: requests; extra == 'test-all'
Requires-Dist: shiny; extra == 'test-all'
Requires-Dist: shinywidgets; extra == 'test-all'
Requires-Dist: streamlit; extra == 'test-all'
Requires-Dist: tomli; (python_version < '3.11') and extra == 'test-all'
Requires-Dist: traitlets; extra == 'test-all'
Requires-Dist: typeguard>=4.4.1; extra == 'test-all'
Requires-Dist: typing-extensions; extra == 'test-all'
Requires-Dist: typing-extensions; (python_version < '3.11') and extra == 'test-all'
Requires-Dist: world-bank-data; extra == 'test-all'
Provides-Extra: test-base
Requires-Dist: pytest; extra == 'test-base'
Requires-Dist: pytest-cov; extra == 'test-base'
Requires-Dist: pytest-xdist; extra == 'test-base'
Provides-Extra: test-dash
Requires-Dist: dash; extra == 'test-dash'
Requires-Dist: pytest; extra == 'test-dash'
Requires-Dist: pytest-cov; extra == 'test-dash'
Requires-Dist: pytest-xdist; extra == 'test-dash'
Requires-Dist: typing-extensions; extra == 'test-dash'
Provides-Extra: test-notebook
Requires-Dist: anywidget; extra == 'test-notebook'
Requires-Dist: ipykernel; extra == 'test-notebook'
Requires-Dist: ipython; extra == 'test-notebook'
Requires-Dist: jupytext; extra == 'test-notebook'
Requires-Dist: nbconvert; extra == 'test-notebook'
Requires-Dist: pytest; extra == 'test-notebook'
Requires-Dist: pytest-cov; extra == 'test-notebook'
Requires-Dist: pytest-xdist; extra == 'test-notebook'
Requires-Dist: requests; extra == 'test-notebook'
Requires-Dist: traitlets; extra == 'test-notebook'
Provides-Extra: typing
Requires-Dist: typing-extensions; (python_version < '3.11') and extra == 'typing'
Provides-Extra: widget
Requires-Dist: anywidget; extra == 'widget'
Requires-Dist: traitlets; extra == 'widget'
